sas_yolov7/__init__.py
sas_yolov7/detect.py
sas_yolov7/export.py
sas_yolov7/hubconf.py
sas_yolov7/requirements.txt
sas_yolov7/test.py
sas_yolov7/train.py
sas_yolov7/train_aux.py
sas_yolov7/cfg/baseline/r50-csp.yaml
sas_yolov7/cfg/baseline/x50-csp.yaml
sas_yolov7/cfg/baseline/yolor-csp-x.yaml
sas_yolov7/cfg/baseline/yolor-csp.yaml
sas_yolov7/cfg/baseline/yolor-d6.yaml
sas_yolov7/cfg/baseline/yolor-e6.yaml
sas_yolov7/cfg/baseline/yolor-p6.yaml
sas_yolov7/cfg/baseline/yolor-w6.yaml
sas_yolov7/cfg/baseline/yolov3-spp.yaml
sas_yolov7/cfg/baseline/yolov3.yaml
sas_yolov7/cfg/baseline/yolov4-csp.yaml
sas_yolov7/cfg/deploy/yolov7-d6.yaml
sas_yolov7/cfg/deploy/yolov7-e6.yaml
sas_yolov7/cfg/deploy/yolov7-e6e.yaml
sas_yolov7/cfg/deploy/yolov7-tiny-silu.yaml
sas_yolov7/cfg/deploy/yolov7-tiny.yaml
sas_yolov7/cfg/deploy/yolov7-w6.yaml
sas_yolov7/cfg/deploy/yolov7.yaml
sas_yolov7/cfg/deploy/yolov7x.yaml
sas_yolov7/cfg/training/yolov7-d6.yaml
sas_yolov7/cfg/training/yolov7-e6.yaml
sas_yolov7/cfg/training/yolov7-e6e.yaml
sas_yolov7/cfg/training/yolov7-tiny.yaml
sas_yolov7/cfg/training/yolov7-w6.yaml
sas_yolov7/cfg/training/yolov7.yaml
sas_yolov7/cfg/training/yolov7x.yaml
sas_yolov7/data/coco.yaml
sas_yolov7/data/hyp.scratch.custom.yaml
sas_yolov7/data/hyp.scratch.p5.yaml
sas_yolov7/data/hyp.scratch.p6.yaml
sas_yolov7/data/hyp.scratch.tiny.yaml
sas_yolov7/deploy/triton-inference-server/README.md
sas_yolov7/deploy/triton-inference-server/data/dog.jpg
sas_yolov7/deploy/triton-inference-server/data/dog_result.jpg
sas_yolov7/figure/horses_prediction.jpg
sas_yolov7/figure/mask.png
sas_yolov7/figure/performance.png
sas_yolov7/figure/pose.png
sas_yolov7/figure/tennis.jpg
sas_yolov7/figure/tennis_caption.png
sas_yolov7/figure/tennis_panoptic.png
sas_yolov7/figure/tennis_semantic.jpg
sas_yolov7/figure/yolov7_3d.jpg
sas_yolov7/figure/yolov7_city.jpg
sas_yolov7/figure/yolov7_lidar.jpg
sas_yolov7/figure/yolov7_road.jpg
sas_yolov7/inference/images/bus.jpg
sas_yolov7/inference/images/horses.jpg
sas_yolov7-1.0.3.dist-info/LICENSE
sas_yolov7-1.0.3.dist-info/LICENSE.md
sas_yolov7-1.0.3.dist-info/METADATA
sas_yolov7-1.0.3.dist-info/WHEEL
sas_yolov7-1.0.3.dist-info/top_level.txt
sas_yolov7-1.0.3.dist-info/RECORD
