Metadata-Version: 2.1
Name: sas-yolov7
Version: 1.0.3
Summary: SAS YOLOv7
Home-page: https://github.com/sassoftware/yolov7/
Author: SAS
Author-email: support@sas.com
License: GNU GENERAL PUBLIC LICENSE 3.0
Classifier: Development Status :: 5 - Production/Stable
Classifier: Environment :: Console
Classifier: Intended Audience :: Science/Research
Classifier: Programming Language :: Python :: 3.7
Classifier: Topic :: Scientific/Engineering
License-File: LICENSE
License-File: LICENSE.md
